Workbook

Sheet Summary
A1: Loan Schedules - Summary
A3: Facility | B3: Value date | C3: Principal amount | D3: No. of installments | E3: Interest rate (annual) | F3: Interest / commission received in advance
A4: ='Tawaruq Loan'!A1 -> Tawaruq Loan - Amortization / Discount Schedule | B4: ='Tawaruq Loan'!B3 -> 2023/07/20 | C4: ='Tawaruq Loan'!E3 -> 3000000 | D4: ='Tawaruq Loan'!B4 -> 60 | E4: ='Tawaruq Loan'!B5 -> 0.0985 | F4: ='Tawaruq Loan'!E4 -> -762868.84
A5: ='Discounted Bills 1'!A1 -> Discounted Bills (Loan 1) - Amortization Schedule | B5: ='Discounted Bills 1'!B3 -> 8/9/2022 | C5: ='Discounted Bills 1'!E3 -> 3750000 | D5: ='Discounted Bills 1'!B4 -> 60 | E5: ='Discounted Bills 1'!B5 -> 0.0984 | F5: ='Discounted Bills 1'!E4 -> -950721.65
A6: ='Discounted Bills 2'!A1 -> Discounted Bills (Loan 2) - Amortization Schedule | B6: ='Discounted Bills 2'!B3 -> 9/14/2022 | C6: ='Discounted Bills 2'!E3 -> 2500000 | D6: ='Discounted Bills 2'!B4 -> 60 | E6: ='Discounted Bills 2'!B5 -> 0.0984 | F6: ='Discounted Bills 2'!E4 -> -634110.51
A7: Total | C7: =SUM(C4:C6) -> 9250000 | F7: =SUM(F4:F6) -> -2347701
A9: Source: 4940_001.pdf (scanned bank amortization schedules). Each facility's full 60-month schedule is on its own tab. Blue cells are source inputs; all other figures are formulas.

Sheet Tawaruq Loan
A1: Tawaruq Loan - Amortization / Discount Schedule
A3: Value date | B3: 2023/07/20 | D3: Principal amount | E3: 3000000
A4: Number of installments | B4: 60 | D4: Interest received in advance | E4: =-D71 -> -762868.84
A5: Interest rate (annual) | B5: 0.0985
A7: Value date (period start) | B7: 45127
A8: First installment date | B8: 45158
A10: No. | B10: Date | C10: No. of days | D10: Commission on beginning balance | E10: Beginning balance | F10: Principal installment | G10: Ending balance
A11: 1 | B11: ='Tawaruq Loan'!$B$8 -> 45158 | C11: =B11-'Tawaruq Loan'!$B$7 -> 31 | D11: =ROUND(E11*'Tawaruq Loan'!$B$5*C11/360,2) -> 25445.83 | E11: ='Tawaruq Loan'!$E$3 -> 3000000 | F11: =ROUND('Tawaruq Loan'!$E$3/'Tawaruq Loan'!$B$4,2) -> 50000 | G11: =E11-F11 -> 2950000
A12: 2 | B12: =EDATE(B11,1) -> 45189 | C12: =B12-B11 -> 31 | D12: =ROUND(E12*'Tawaruq Loan'!$B$5*C12/360,2) -> 25021.74 | E12: =G11 -> 2950000 | F12: =ROUND('Tawaruq Loan'!$E$3/'Tawaruq Loan'!$B$4,2) -> 50000 | G12: =E12-F12 -> 2900000
A13: 3 | B13: =EDATE(B12,1) -> 45219 | C13: =B13-B12 -> 30 | D13: =ROUND(E13*'Tawaruq Loan'!$B$5*C13/360,2) -> 23804.17 | E13: =G12 -> 2900000 | F13: =ROUND('Tawaruq Loan'!$E$3/'Tawaruq Loan'!$B$4,2) -> 50000 | G13: =E13-F13 -> 2850000
A14: 4 | B14: =EDATE(B13,1) -> 45250 | C14: =B14-B13 -> 31 | D14: =ROUND(E14*'Tawaruq Loan'!$B$5*C14/360,2) -> 24173.54 | E14: =G13 -> 2850000 | F14: =ROUND('Tawaruq Loan'!$E$3/'Tawaruq Loan'!$B$4,2) -> 50000 | G14: =E14-F14 -> 2800000
A15: 5 | B15: =EDATE(B14,1) -> 45280 | C15: =B15-B14 -> 30 | D15: =ROUND(E15*'Tawaruq Loan'!$B$5*C15/360,2) -> 22983.33 | E15: =G14 -> 2800000 | F15: =ROUND('Tawaruq Loan'!$E$3/'Tawaruq Loan'!$B$4,2) -> 50000 | G15: =E15-F15 -> 2750000
A16: 6 | B16: =EDATE(B15,1) -> 45311 | C16: =B16-B15 -> 31 | D16: =ROUND(E16*'Tawaruq Loan'!$B$5*C16/360,2) -> 23325.35 | E16: =G15 -> 2750000 | F16: =ROUND('Tawaruq Loan'!$E$3/'Tawaruq Loan'!$B$4,2) -> 50000 | G16: =E16-F16 -> 2700000
A17: 7 | B17: =EDATE(B16,1) -> 45342 | C17: =B17-B16 -> 31 | D17: =ROUND(E17*'Tawaruq Loan'!$B$5*C17/360,2) -> 22901.25 | E17: =G16 -> 2700000 | F17: =ROUND('Tawaruq Loan'!$E$3/'Tawaruq Loan'!$B$4,2) -> 50000 | G17: =E17-F17 -> 2650000
A18: 8 | B18: =EDATE(B17,1) -> 45371 | C18: =B18-B17 -> 29 | D18: =ROUND(E18*'Tawaruq Loan'!$B$5*C18/360,2) -> 21027.01 | E18: =G17 -> 2650000 | F18: =ROUND('Tawaruq Loan'!$E$3/'Tawaruq Loan'!$B$4,2) -> 50000 | G18: =E18-F18 -> 2600000
A19: 9 | B19: =EDATE(B18,1) -> 45402 | C19: =B19-B18 -> 31 | D19: =ROUND(E19*'Tawaruq Loan'!$B$5*C19/360,2) -> 22053.06 | E19: =G18 -> 2600000 | F19: =ROUND('Tawaruq Loan'!$E$3/'Tawaruq Loan'!$B$4,2) -> 50000 | G19: =E19-F19 -> 2550000
A20: 10 | B20: =EDATE(B19,1) -> 45432 | C20: =B20-B19 -> 30 | D20: =ROUND(E20*'Tawaruq Loan'!$B$5*C20/360,2) -> 20931.25 | E20: =G19 -> 2550000 | F20: =ROUND('Tawaruq Loan'!$E$3/'Tawaruq Loan'!$B$4,2) -> 50000 | G20: =E20-F20 -> 2500000
A21: 11 | B21: =EDATE(B20,1) -> 45463 | C21: =B21-B20 -> 31 | D21: =ROUND(E21*'Tawaruq Loan'!$B$5*C21/360,2) -> 21204.86 | E21: =G20 -> 2500000 | F21: =ROUND('Tawaruq Loan'!$E$3/'Tawaruq Loan'!$B$4,2) -> 50000 | G21: =E21-F21 -> 2450000
A22: 12 | B22: =EDATE(B21,1) -> 45493 | C22: =B22-B21 -> 30 | D22: =ROUND(E22*'Tawaruq Loan'!$B$5*C22/360,2) -> 20110.42 | E22: =G21 -> 2450000 | F22: =ROUND('Tawaruq Loan'!$E$3/'Tawaruq Loan'!$B$4,2) -> 50000 | G22: =E22-F22 -> 2400000
A23: 13 | B23: =EDATE(B22,1) -> 45524 | C23: =B23-B22 -> 31 | D23: =ROUND(E23*'Tawaruq Loan'!$B$5*C23/360,2) -> 20356.67 | E23: =G22 -> 2400000 | F23: =ROUND('Tawaruq Loan'!$E$3/'Tawaruq Loan'!$B$4,2) -> 50000 | G23: =E23-F23 -> 2350000
... A69: 59 | B69: =EDATE(B68,1) -> 46924 | C69: =B69-B68 -> 31 | D69: =ROUND(E69*'Tawaruq Loan'!$B$5*C69/360,2) -> 848.19 | E69: =G68 -> 100000 | F69: =ROUND('Tawaruq Loan'!$E$3/'Tawaruq Loan'!$B$4,2) -> 50000 | G69: =E69-F69 -> 50000
A70: 60 | B70: =EDATE(B69,1) -> 46954 | C70: =B70-B69 -> 30 | D70: =ROUND(E70*'Tawaruq Loan'!$B$5*C70/360,2) -> 410.42 | E70: =G69 -> 50000 | F70: =E70 -> 50000 | G70: =E70-F70 -> 0
C71: Total: | D71: =SUM(D11:D70) -> 762868.84 | F71: =SUM(F11:F70) -> 3000000
A73: Note: Commission = ROUND(Beginning balance x Annual rate x Days/360, 2). Principal installment is flat (Principal/No. of installments), with the final installment absorbing any rounding difference so the ending balance reaches exactly zero. Source: scanned bank amortization schedule (4940_001.pdf).

Sheet Discounted Bills 1
A1: Discounted Bills (Loan 1) - Amortization Schedule
A3: Value date | B3: 8/9/2022 | D3: Principal amount | E3: 3750000
A4: Number of installments | B4: 60 | D4: Interest received in advance | E4: =-D71 -> -950721.65
A5: Interest rate (annual) | B5: 0.0984
D6: Net amount credited to customer | E6: ='Discounted Bills 1'!$E$3+'Discounted Bills 1'!$E$4 -> 2799278.4
A7: Value date (period start) | B7: 44782
A8: First installment date | B8: 44812
A10: No. | B10: Date | C10: No. of days | D10: Commission on beginning balance | E10: Beginning balance | F10: Principal installment | G10: Ending balance
A11: 1 | B11: ='Discounted Bills 1'!$B$8 -> 44812 | C11: =B11-'Discounted Bills 1'!$B$7 -> 30 | D11: =ROUND(E11*'Discounted Bills 1'!$B$5*C11/360,2) -> 30750 | E11: ='Discounted Bills 1'!$E$3 -> 3750000 | F11: =ROUND('Discounted Bills 1'!$E$3/'Discounted Bills 1'!$B$4,2) -> 62500 | G11: =E11-F11 -> 3687500
A12: 2 | B12: =EDATE(B11,1) -> 44842 | C12: =B12-B11 -> 30 | D12: =ROUND(E12*'Discounted Bills 1'!$B$5*C12/360,2) -> 30237.5 | E12: =G11 -> 3687500 | F12: =ROUND('Discounted Bills 1'!$E$3/'Discounted Bills 1'!$B$4,2) -> 62500 | G12: =E12-F12 -> 3625000
A13: 3 | B13: =EDATE(B12,1) -> 44873 | C13: =B13-B12 -> 31 | D13: =ROUND(E13*'Discounted Bills 1'!$B$5*C13/360,2) -> 30715.83 | E13: =G12 -> 3625000 | F13: =ROUND('Discounted Bills 1'!$E$3/'Discounted Bills 1'!$B$4,2) -> 62500 | G13: =E13-F13 -> 3562500
A14: 4 | B14: =EDATE(B13,1) -> 44903 | C14: =B14-B13 -> 30 | D14: =ROUND(E14*'Discounted Bills 1'!$B$5*C14/360,2) -> 29212.5 | E14: =G13 -> 3562500 | F14: =ROUND('Discounted Bills 1'!$E$3/'Discounted Bills 1'!$B$4,2) -> 62500 | G14: =E14-F14 -> 3500000
A15: 5 | B15: =EDATE(B14,1) -> 44934 | C15: =B15-B14 -> 31 | D15: =ROUND(E15*'Discounted Bills 1'!$B$5*C15/360,2) -> 29656.67 | E15: =G14 -> 3500000 | F15: =ROUND('Discounted Bills 1'!$E$3/'Discounted Bills 1'!$B$4,2) -> 62500 | G15: =E15-F15 -> 3437500
A16: 6 | B16: =EDATE(B15,1) -> 44965 | C16: =B16-B15 -> 31 | D16: =ROUND(E16*'Discounted Bills 1'!$B$5*C16/360,2) -> 29127.08 | E16: =G15 -> 3437500 | F16: =ROUND('Discounted Bills 1'!$E$3/'Discounted Bills 1'!$B$4,2) -> 62500 | G16: =E16-F16 -> 3375000
A17: 7 | B17: =EDATE(B16,1) -> 44993 | C17: =B17-B16 -> 28 | D17: =ROUND(E17*'Discounted Bills 1'!$B$5*C17/360,2) -> 25830 | E17: =G16 -> 3375000 | F17: =ROUND('Discounted Bills 1'!$E$3/'Discounted Bills 1'!$B$4,2) -> 62500 | G17: =E17-F17 -> 3312500
A18: 8 | B18: =EDATE(B17,1) -> 45024 | C18: =B18-B17 -> 31 | D18: =ROUND(E18*'Discounted Bills 1'!$B$5*C18/360,2) -> 28067.92 | E18: =G17 -> 3312500 | F18: =ROUND('Discounted Bills 1'!$E$3/'Discounted Bills 1'!$B$4,2) -> 62500 | G18: =E18-F18 -> 3250000
A19: 9 | B19: =EDATE(B18,1) -> 45054 | C19: =B19-B18 -> 30 | D19: =ROUND(E19*'Discounted Bills 1'!$B$5*C19/360,2) -> 26650 | E19: =G18 -> 3250000 | F19: =ROUND('Discounted Bills 1'!$E$3/'Discounted Bills 1'!$B$4,2) -> 62500 | G19: =E19-F19 -> 3187500
A20: 10 | B20: =EDATE(B19,1) -> 45085 | C20: =B20-B19 -> 31 | D20: =ROUND(E20*'Discounted Bills 1'!$B$5*C20/360,2) -> 27008.75 | E20: =G19 -> 3187500 | F20: =ROUND('Discounted Bills 1'!$E$3/'Discounted Bills 1'!$B$4,2) -> 62500 | G20: =E20-F20 -> 3125000
A21: 11 | B21: =EDATE(B20,1) -> 45115 | C21: =B21-B20 -> 30 | D21: =ROUND(E21*'Discounted Bills 1'!$B$5*C21/360,2) -> 25625 | E21: =G20 -> 3125000 | F21: =ROUND('Discounted Bills 1'!$E$3/'Discounted Bills 1'!$B$4,2) -> 62500 | G21: =E21-F21 -> 3062500
A22: 12 | B22: =EDATE(B21,1) -> 45146 | C22: =B22-B21 -> 31 | D22: =ROUND(E22*'Discounted Bills 1'!$B$5*C22/360,2) -> 25949.58 | E22: =G21 -> 3062500 | F22: =ROUND('Discounted Bills 1'!$E$3/'Discounted Bills 1'!$B$4,2) -> 62500 | G22: =E22-F22 -> 3000000
A23: 13 | B23: =EDATE(B22,1) -> 45177 | C23: =B23-B22 -> 31 | D23: =ROUND(E23*'Discounted Bills 1'!$B$5*C23/360,2) -> 25420 | E23: =G22 -> 3000000 | F23: =ROUND('Discounted Bills 1'!$E$3/'Discounted Bills 1'!$B$4,2) -> 62500 | G23: =E23-F23 -> 2937500
... A69: 59 | B69: =EDATE(B68,1) -> 46576 | C69: =B69-B68 -> 30 | D69: =ROUND(E69*'Discounted Bills 1'!$B$5*C69/360,2) -> 1025 | E69: =G68 -> 125000 | F69: =ROUND('Discounted Bills 1'!$E$3/'Discounted Bills 1'!$B$4,2) -> 62500 | G69: =E69-F69 -> 62500
A70: 60 | B70: =EDATE(B69,1) -> 46607 | C70: =B70-B69 -> 31 | D70: =ROUND(E70*'Discounted Bills 1'!$B$5*C70/360,2) -> 529.58 | E70: =G69 -> 62500 | F70: =E70 -> 62500 | G70: =E70-F70 -> 0
C71: Total: | D71: =SUM(D11:D70) -> 950721.65 | F71: =SUM(F11:F70) -> 3750000
A73: Note: Commission = ROUND(Beginning balance x Annual rate x Days/360, 2). Principal installment is flat (Principal/No. of installments), with the final installment absorbing any rounding difference so the ending balance reaches exactly zero. Source: scanned bank amortization schedule (4940_001.pdf).

Sheet Discounted Bills 2
A1: Discounted Bills (Loan 2) - Amortization Schedule
A3: Value date | B3: 9/14/2022 | D3: Principal amount | E3: 2500000
A4: Number of installments | B4: 60 | D4: Interest received in advance | E4: =-D71 -> -634110.51
A5: Interest rate (annual) | B5: 0.0984
D6: Net amount credited to customer | E6: ='Discounted Bills 2'!$E$3+'Discounted Bills 2'!$E$4 -> 1865889.5
A7: Value date (period start) | B7: 44818
A8: First installment date | B8: 44848
A10: No. | B10: Date | C10: No. of days | D10: Commission on beginning balance | E10: Beginning balance | F10: Principal installment | G10: Ending balance
A11: 1 | B11: ='Discounted Bills 2'!$B$8 -> 44848 | C11: =B11-'Discounted Bills 2'!$B$7 -> 30 | D11: =ROUND(E11*'Discounted Bills 2'!$B$5*C11/360,2) -> 20500 | E11: ='Discounted Bills 2'!$E$3 -> 2500000 | F11: =ROUND('Discounted Bills 2'!$E$3/'Discounted Bills 2'!$B$4,2) -> 41666.67 | G11: =E11-F11 -> 2458333.3
A12: 2 | B12: =EDATE(B11,1) -> 44879 | C12: =B12-B11 -> 31 | D12: =ROUND(E12*'Discounted Bills 2'!$B$5*C12/360,2) -> 20830.28 | E12: =G11 -> 2458333.3 | F12: =ROUND('Discounted Bills 2'!$E$3/'Discounted Bills 2'!$B$4,2) -> 41666.67 | G12: =E12-F12 -> 2416666.7
A13: 3 | B13: =EDATE(B12,1) -> 44909 | C13: =B13-B12 -> 30 | D13: =ROUND(E13*'Discounted Bills 2'!$B$5*C13/360,2) -> 19816.67 | E13: =G12 -> 2416666.7 | F13: =ROUND('Discounted Bills 2'!$E$3/'Discounted Bills 2'!$B$4,2) -> 41666.67 | G13: =E13-F13 -> 2375000
A14: 4 | B14: =EDATE(B13,1) -> 44940 | C14: =B14-B13 -> 31 | D14: =ROUND(E14*'Discounted Bills 2'!$B$5*C14/360,2) -> 20124.17 | E14: =G13 -> 2375000 | F14: =ROUND('Discounted Bills 2'!$E$3/'Discounted Bills 2'!$B$4,2) -> 41666.67 | G14: =E14-F14 -> 2333333.3
A15: 5 | B15: =EDATE(B14,1) -> 44971 | C15: =B15-B14 -> 31 | D15: =ROUND(E15*'Discounted Bills 2'!$B$5*C15/360,2) -> 19771.11 | E15: =G14 -> 2333333.3 | F15: =ROUND('Discounted Bills 2'!$E$3/'Discounted Bills 2'!$B$4,2) -> 41666.67 | G15: =E15-F15 -> 2291666.6
A16: 6 | B16: =EDATE(B15,1) -> 44999 | C16: =B16-B15 -> 28 | D16: =ROUND(E16*'Discounted Bills 2'!$B$5*C16/360,2) -> 17538.89 | E16: =G15 -> 2291666.6 | F16: =ROUND('Discounted Bills 2'!$E$3/'Discounted Bills 2'!$B$4,2) -> 41666.67 | G16: =E16-F16 -> 2250000
A17: 7 | B17: =EDATE(B16,1) -> 45030 | C17: =B17-B16 -> 31 | D17: =ROUND(E17*'Discounted Bills 2'!$B$5*C17/360,2) -> 19065 | E17: =G16 -> 2250000 | F17: =ROUND('Discounted Bills 2'!$E$3/'Discounted Bills 2'!$B$4,2) -> 41666.67 | G17: =E17-F17 -> 2208333.3
A18: 8 | B18: =EDATE(B17,1) -> 45060 | C18: =B18-B17 -> 30 | D18: =ROUND(E18*'Discounted Bills 2'!$B$5*C18/360,2) -> 18108.33 | E18: =G17 -> 2208333.3 | F18: =ROUND('Discounted Bills 2'!$E$3/'Discounted Bills 2'!$B$4,2) -> 41666.67 | G18: =E18-F18 -> 2166666.6
A19: 9 | B19: =EDATE(B18,1) -> 45091 | C19: =B19-B18 -> 31 | D19: =ROUND(E19*'Discounted Bills 2'!$B$5*C19/360,2) -> 18358.89 | E19: =G18 -> 2166666.6 | F19: =ROUND('Discounted Bills 2'!$E$3/'Discounted Bills 2'!$B$4,2) -> 41666.67 | G19: =E19-F19 -> 2125000
A20: 10 | B20: =EDATE(B19,1) -> 45121 | C20: =B20-B19 -> 30 | D20: =ROUND(E20*'Discounted Bills 2'!$B$5*C20/360,2) -> 17425 | E20: =G19 -> 2125000 | F20: =ROUND('Discounted Bills 2'!$E$3/'Discounted Bills 2'!$B$4,2) -> 41666.67 | G20: =E20-F20 -> 2083333.3
A21: 11 | B21: =EDATE(B20,1) -> 45152 | C21: =B21-B20 -> 31 | D21: =ROUND(E21*'Discounted Bills 2'!$B$5*C21/360,2) -> 17652.78 | E21: =G20 -> 2083333.3 | F21: =ROUND('Discounted Bills 2'!$E$3/'Discounted Bills 2'!$B$4,2) -> 41666.67 | G21: =E21-F21 -> 2041666.6
A22: 12 | B22: =EDATE(B21,1) -> 45183 | C22: =B22-B21 -> 31 | D22: =ROUND(E22*'Discounted Bills 2'!$B$5*C22/360,2) -> 17299.72 | E22: =G21 -> 2041666.6 | F22: =ROUND('Discounted Bills 2'!$E$3/'Discounted Bills 2'!$B$4,2) -> 41666.67 | G22: =E22-F22 -> 2000000
A23: 13 | B23: =EDATE(B22,1) -> 45213 | C23: =B23-B22 -> 30 | D23: =ROUND(E23*'Discounted Bills 2'!$B$5*C23/360,2) -> 16400 | E23: =G22 -> 2000000 | F23: =ROUND('Discounted Bills 2'!$E$3/'Discounted Bills 2'!$B$4,2) -> 41666.67 | G23: =E23-F23 -> 1958333.3
... A69: 59 | B69: =EDATE(B68,1) -> 46613 | C69: =B69-B68 -> 31 | D69: =ROUND(E69*'Discounted Bills 2'!$B$5*C69/360,2) -> 706.11 | E69: =G68 -> 83333.14 | F69: =ROUND('Discounted Bills 2'!$E$3/'Discounted Bills 2'!$B$4,2) -> 41666.67 | G69: =E69-F69 -> 41666.47
A70: 60 | B70: =EDATE(B69,1) -> 46644 | C70: =B70-B69 -> 31 | D70: =ROUND(E70*'Discounted Bills 2'!$B$5*C70/360,2) -> 353.05 | E70: =G69 -> 41666.47 | F70: =E70 -> 41666.47 | G70: =E70-F70 -> 0
C71: Total: | D71: =SUM(D11:D70) -> 634110.51 | F71: =SUM(F11:F70) -> 2500000
A73: Note: Commission = ROUND(Beginning balance x Annual rate x Days/360, 2). Principal installment is flat (Principal/No. of installments), with the final installment absorbing any rounding difference so the ending balance reaches exactly zero. Source: scanned bank amortization schedule (4940_001.pdf).
